magic_dot/__init__.py
magic_dot/exceptions.py
magic_dot-0.2.0.dist-info/AUTHORS.rst
magic_dot-0.2.0.dist-info/LICENSE
magic_dot-0.2.0.dist-info/METADATA
magic_dot-0.2.0.dist-info/WHEEL
magic_dot-0.2.0.dist-info/top_level.txt
magic_dot-0.2.0.dist-info/RECORD
