Metadata-Version: 2.1
Name: magic-dot
Version: 0.2.0
Summary: Library that allows deep extraction of layered data structures (like JSON).
Home-page: https://github.com/bonafideduck/magic_dot
Author: Mark Eklund
Author-email: magic_dot@patnan.com
License: BSD license
Keywords: magic_dot
Platform: UNKNOWN
Classifier: Development Status :: 2 - Pre-Alpha
Classifier: Intended Audience :: Developers
Classifier: License :: OSI Approved :: BSD License
Classifier: Natural Language :: English
Classifier: Programming Language :: Python :: 3
Classifier: Programming Language :: Python :: 3.5
Classifier: Programming Language :: Python :: 3.6
Classifier: Programming Language :: Python :: 3.7
Classifier: Programming Language :: Python :: 3.8
Requires-Python: >=3.5
